xiplot/__init__.py
xiplot/__main__.py
xiplot/app.py
xiplot/plugin.py
xiplot/setup.py
xiplot/assets/RDKit_minimal.js
xiplot/assets/RDKit_minimal.wasm
xiplot/assets/__init__.py
xiplot/assets/book.svg
xiplot/assets/dcc_style.css
xiplot/assets/favicon.ico
xiplot/assets/github.svg
xiplot/assets/html_components.css
xiplot/assets/stylesheet.css
xiplot/plots/__init__.py
xiplot/plots/barplot.py
xiplot/plots/boxplot.py
xiplot/plots/distplot.py
xiplot/plots/heatmap.py
xiplot/plots/histogram.py
xiplot/plots/lineplot.py
xiplot/plots/scatterplot.py
xiplot/plots/smiles.py
xiplot/plots/table.py
xiplot/tabs/__init__.py
xiplot/tabs/cluster.py
xiplot/tabs/data.py
xiplot/tabs/embedding.py
xiplot/tabs/plots.py
xiplot/tabs/plugins.py
xiplot/tabs/settings.py
xiplot/utils/__init__.py
xiplot/utils/auxiliary.py
xiplot/utils/cli.py
xiplot/utils/cluster.py
xiplot/utils/components.py
xiplot/utils/dataframe.py
xiplot/utils/io.py
xiplot/utils/layouts.py
xiplot/utils/regex.py
xiplot/utils/scatterplot.py
xiplot/utils/store.py
xiplot/utils/table.py
xiplot-0.4.1.dist-info/LICENSE-MIT
xiplot-0.4.1.dist-info/METADATA
xiplot-0.4.1.dist-info/WHEEL
xiplot-0.4.1.dist-info/entry_points.txt
xiplot-0.4.1.dist-info/top_level.txt
xiplot-0.4.1.dist-info/RECORD
