Metadata-Version: 2.1
Name: xiplot
Version: 0.4.1
Summary: Interactive data visualization tool
Author: Anton Björklund, Jarmo Mäkelä
Author-email: Akihiro Tanaka <akihiro.fin@gmail.com>, Juniper Tyree <juniper.tyree@helsinki.fi>
License: MIT License
Project-URL: homepage, https://github.com/edahelsinki/xiplot
Project-URL: repository, https://github.com/edahelsinki/xiplot.git
Keywords: Visalisation,Virtual Laboratory,Exploratory Data Analysis
Classifier: Programming Language :: Python :: 3
Classifier: License :: OSI Approved :: MIT License
Classifier: Operating System :: OS Independent
Classifier: Topic :: Scientific/Engineering :: Artificial Intelligence
Classifier: Topic :: Scientific/Engineering :: Visualization
Requires-Python: >=3.7
License-File: LICENSE-MIT
Requires-Dist: dash ==2.6.2
Requires-Dist: dash-extensions ==0.1.4
Requires-Dist: dash-mantine-components ==0.10.2
Requires-Dist: pandas <2.0.0,>=1.4.0
Requires-Dist: plotly >=5.9.0
Requires-Dist: Werkzeug <3.0.0
Requires-Dist: dash-uploader ~=0.6.0 ; platform_system != "Emscripten"
Requires-Dist: jsonschema ~=4.6.0 ; platform_system != "Emscripten"
Requires-Dist: kaleido ~=0.2.1 ; platform_system != "Emscripten"
Requires-Dist: scikit-learn >=1.0 ; platform_system != "Emscripten"
Requires-Dist: xiplot-filetypes ==1.0 ; platform_system != "Emscripten"
Provides-Extra: dev
Requires-Dist: pytest ; extra == 'dev'
Requires-Dist: black ; extra == 'dev'
Requires-Dist: dash[testing] ; extra == 'dev'
Requires-Dist: isort ; extra == 'dev'
Requires-Dist: pyproject-flake8 ; extra == 'dev'
Requires-Dist: webdriver-manager ; extra == 'dev'
Requires-Dist: selenium ; extra == 'dev'
Requires-Dist: IPython ; extra == 'dev'
